ibb_api_arsivi/__init__.py
ibb_api_arsivi/ispark.py
ibb_api_arsivi-0.1.0.dist-info/LICENSE
ibb_api_arsivi-0.1.0.dist-info/METADATA
ibb_api_arsivi-0.1.0.dist-info/WHEEL
ibb_api_arsivi-0.1.0.dist-info/top_level.txt
ibb_api_arsivi-0.1.0.dist-info/RECORD
