Metadata-Version: 2.1
Name: ibb_api_arsivi
Version: 0.1.0
Summary: Lorem ipsum dolor sit amet
Author: Ceyda Özarslan
Author-email: ceyzarslan@gmail.com
Classifier: Programming Language :: Python :: 3
Classifier: License :: OSI Approved :: MIT License
Classifier: Operating System :: OS Independent
Requires-Python: >=3.6
License-File: LICENSE
Requires-Dist: pandas
Requires-Dist: requests
